setup.py
arcapi/__init__.py
arcapi/api.py
arcapi/util.py
arcapi.egg-info/PKG-INFO
arcapi.egg-info/SOURCES.txt
arcapi.egg-info/dependency_links.txt
arcapi.egg-info/requires.txt
arcapi.egg-info/top_level.txt